{
    "available_space": true,
    "content": [
        {
            "id": "Tsng-XrlOvc",
            "name": "The Best of Dvorak 2 [Tsng-XrlOvc].mp4",
            "path": "/home/alanmatzumiya/Videos/container/m4/videos/The Best of Dvorak 2 [Tsng-XrlOvc].mp4",
            "size": 87.249414,
            "url": "https://github.com/circuitalmynds/music_m4/blob/main/videos/The Best of Dvorak 2 [Tsng-XrlOvc].mp4?raw=true"
        },
        {
            "id": "dBhEEQ1XoT0",
            "name": "\u5bae\u4e0b\u5bcc\u5b9f\u592b   2004 01 28   ETERNITY 1 \uff5e BEST OF HEALING [dBhEEQ1XoT0].mp4",
            "path": "/home/alanmatzumiya/Videos/container/m4/videos/\u5bae\u4e0b\u5bcc\u5b9f\u592b   2004 01 28   ETERNITY 1 \uff5e BEST OF HEALING [dBhEEQ1XoT0].mp4",
            "size": 52.458318999999996,
            "url": "https://github.com/circuitalmynds/music_m4/blob/main/videos/\u5bae\u4e0b\u5bcc\u5b9f\u592b   2004 01 28   ETERNITY 1 \uff5e BEST OF HEALING [dBhEEQ1XoT0].mp4?raw=true"
        },
        {
            "id": "otFVFLtRF_s",
            "name": "Cantaloupe Island (Remastered 1999\u29f8Rudy Van Gelder Edition) [otFVFLtRF_s].mp4",
            "path": "/home/alanmatzumiya/Videos/container/m4/videos/Cantaloupe Island (Remastered 1999\u29f8Rudy Van Gelder Edition) [otFVFLtRF_s].mp4",
            "size": 7.061315,
            "url": "https://github.com/circuitalmynds/music_m4/blob/main/videos/Cantaloupe Island (Remastered 1999\u29f8Rudy Van Gelder Edition) [otFVFLtRF_s].mp4?raw=true"
        },
        {
            "id": "itGzQb-Rc8k",
            "name": "Les Yeux Noirs [itGzQb-Rc8k].mp4",
            "path": "/home/alanmatzumiya/Videos/container/m4/videos/Les Yeux Noirs [itGzQb-Rc8k].mp4",
            "size": 5.046755,
            "url": "https://github.com/circuitalmynds/music_m4/blob/main/videos/Les Yeux Noirs [itGzQb-Rc8k].mp4?raw=true"
        },
        {
            "id": "DnDDiPWPqMY",
            "name": "Fusz, J\u00e1nos - Quartet for flute, Viola, Cello and Guitar [DnDDiPWPqMY].mp4",
            "path": "/home/alanmatzumiya/Videos/container/m4/videos/Fusz, J\u00e1nos - Quartet for flute, Viola, Cello and Guitar [DnDDiPWPqMY].mp4",
            "size": 46.651312,
            "url": "https://github.com/circuitalmynds/music_m4/blob/main/videos/Fusz, J\u00e1nos - Quartet for flute, Viola, Cello and Guitar [DnDDiPWPqMY].mp4?raw=true"
        },
        {
            "id": "xS9Ov5tGNgw",
            "name": "A Journey to Russia [xS9Ov5tGNgw].mp4",
            "path": "/home/alanmatzumiya/Videos/container/m4/videos/A Journey to Russia [xS9Ov5tGNgw].mp4",
            "size": 23.751299,
            "url": "https://github.com/circuitalmynds/music_m4/blob/main/videos/A Journey to Russia [xS9Ov5tGNgw].mp4?raw=true"
        },
        {
            "id": "ZpLtqLc3DT0",
            "name": "Liszt - Hungarian Rhapsodies Nos.2,1,3,4,5,6 Orchestra + P\u00b0 (reference recording \uff1a Willi Boskovsky) [ZpLtqLc3DT0].mp4",
            "path": "/home/alanmatzumiya/Videos/container/m4/videos/Liszt - Hungarian Rhapsodies Nos.2,1,3,4,5,6 Orchestra + P\u00b0 (reference recording \uff1a Willi Boskovsky) [ZpLtqLc3DT0].mp4",
            "size": 88.569305,
            "url": "https://github.com/circuitalmynds/music_m4/blob/main/videos/Liszt - Hungarian Rhapsodies Nos.2,1,3,4,5,6 Orchestra + P\u00b0 (reference recording \uff1a Willi Boskovsky) [ZpLtqLc3DT0].mp4?raw=true"
        },
        {
            "id": "NDswc-q62Zs",
            "name": "Symphony No.6 \uff02Chinese Poems\uff02 - Krzysztof Penderecki [NDswc-q62Zs].mp4",
            "path": "/home/alanmatzumiya/Videos/container/m4/videos/Symphony No.6 \uff02Chinese Poems\uff02 - Krzysztof Penderecki [NDswc-q62Zs].mp4",
            "size": 83.600785,
            "url": "https://github.com/circuitalmynds/music_m4/blob/main/videos/Symphony No.6 \uff02Chinese Poems\uff02 - Krzysztof Penderecki [NDswc-q62Zs].mp4?raw=true"
        },
        {
            "id": "5GLm9lKZpx0",
            "name": "J-P.Rameau - Suite from 'Le Temple de la Gloire', Op\u00e9ra-ballet RTC 59 [5GLm9lKZpx0].mp4",
            "path": "/home/alanmatzumiya/Videos/container/m4/videos/J-P.Rameau - Suite from 'Le Temple de la Gloire', Op\u00e9ra-ballet RTC 59 [5GLm9lKZpx0].mp4",
            "size": 43.699141999999995,
            "url": "https://github.com/circuitalmynds/music_m4/blob/main/videos/J-P.Rameau - Suite from 'Le Temple de la Gloire', Op\u00e9ra-ballet RTC 59 [5GLm9lKZpx0].mp4?raw=true"
        },
        {
            "id": "Z5KX_Hw_dHU",
            "name": "Think Twice [Z5KX_Hw_dHU].mp4",
            "path": "/home/alanmatzumiya/Videos/container/m4/videos/Think Twice [Z5KX_Hw_dHU].mp4",
            "size": 15.971205,
            "url": "https://github.com/circuitalmynds/music_m4/blob/main/videos/Think Twice [Z5KX_Hw_dHU].mp4?raw=true"
        },
        {
            "id": "YLnoGZW6eb4",
            "name": "Mozart\uff1a Le nozze di Figaro, K. 492, Act II - Recit. Dunque voi non aprite\uff1f [YLnoGZW6eb4].mp4",
            "path": "/home/alanmatzumiya/Videos/container/m4/videos/Mozart\uff1a Le nozze di Figaro, K. 492, Act II - Recit. Dunque voi non aprite\uff1f [YLnoGZW6eb4].mp4",
            "size": 2.482601,
            "url": "https://github.com/circuitalmynds/music_m4/blob/main/videos/Mozart\uff1a Le nozze di Figaro, K. 492, Act II - Recit. Dunque voi non aprite\uff1f [YLnoGZW6eb4].mp4?raw=true"
        },
        {
            "id": "_EjiSKPzosQ",
            "name": "Belle nuit \u00f4 nuit d'amour (Les Contes D'Hoffman - Offenbach) Score Animation [_EjiSKPzosQ].mp4",
            "path": "/home/alanmatzumiya/Videos/container/m4/videos/Belle nuit \u00f4 nuit d'amour (Les Contes D'Hoffman - Offenbach) Score Animation [_EjiSKPzosQ].mp4",
            "size": 5.002579,
            "url": "https://github.com/circuitalmynds/music_m4/blob/main/videos/Belle nuit \u00f4 nuit d'amour (Les Contes D'Hoffman - Offenbach) Score Animation [_EjiSKPzosQ].mp4?raw=true"
        },
        {
            "id": "6ud7sHucI5c",
            "name": "Carlos Gomes - Grande Valsa de Bravura.wmv [6ud7sHucI5c].mp4",
            "path": "/home/alanmatzumiya/Videos/container/m4/videos/Carlos Gomes - Grande Valsa de Bravura.wmv [6ud7sHucI5c].mp4",
            "size": 15.486015,
            "url": "https://github.com/circuitalmynds/music_m4/blob/main/videos/Carlos Gomes - Grande Valsa de Bravura.wmv [6ud7sHucI5c].mp4?raw=true"
        },
        {
            "id": "HOY6q7NucmM",
            "name": "La condanna [HOY6q7NucmM].mp4",
            "path": "/home/alanmatzumiya/Videos/container/m4/videos/La condanna [HOY6q7NucmM].mp4",
            "size": 4.238073,
            "url": "https://github.com/circuitalmynds/music_m4/blob/main/videos/La condanna [HOY6q7NucmM].mp4?raw=true"
        },
        {
            "id": "anGdIyANsWk",
            "name": "Josef Strauss\uff1a Village Swallows from Austria (1863) [anGdIyANsWk].mp4",
            "path": "/home/alanmatzumiya/Videos/container/m4/videos/Josef Strauss\uff1a Village Swallows from Austria (1863) [anGdIyANsWk].mp4",
            "size": 34.053231,
            "url": "https://github.com/circuitalmynds/music_m4/blob/main/videos/Josef Strauss\uff1a Village Swallows from Austria (1863) [anGdIyANsWk].mp4?raw=true"
        },
        {
            "id": "LevDtrDsLhg",
            "name": "Eduard Strauss I  - Ohne Bremse _ Polka schnell op. 238  _ Musikverein Wien _ #WJSO_AT [LevDtrDsLhg].mp4",
            "path": "/home/alanmatzumiya/Videos/container/m4/videos/Eduard Strauss I  - Ohne Bremse _ Polka schnell op. 238  _ Musikverein Wien _ #WJSO_AT [LevDtrDsLhg].mp4",
            "size": 13.162552,
            "url": "https://github.com/circuitalmynds/music_m4/blob/main/videos/Eduard Strauss I  - Ohne Bremse _ Polka schnell op. 238  _ Musikverein Wien _ #WJSO_AT [LevDtrDsLhg].mp4?raw=true"
        },
        {
            "id": "ZDFrXAaYDyc",
            "name": "Carl Michael Ziehrer - Teuferln (Waltz \u29f8 Walzer) [ZDFrXAaYDyc].mp4",
            "path": "/home/alanmatzumiya/Videos/container/m4/videos/Carl Michael Ziehrer - Teuferln (Waltz \u29f8 Walzer) [ZDFrXAaYDyc].mp4",
            "size": 7.009919999999999,
            "url": "https://github.com/circuitalmynds/music_m4/blob/main/videos/Carl Michael Ziehrer - Teuferln (Waltz \u29f8 Walzer) [ZDFrXAaYDyc].mp4?raw=true"
        },
        {
            "id": "CAzrOF8E28w",
            "name": "Romanyi Rota - Diri, diri so kerdjan [CAzrOF8E28w].mp4",
            "path": "/home/alanmatzumiya/Videos/container/m4/videos/Romanyi Rota - Diri, diri so kerdjan [CAzrOF8E28w].mp4",
            "size": 6.036045,
            "url": "https://github.com/circuitalmynds/music_m4/blob/main/videos/Romanyi Rota - Diri, diri so kerdjan [CAzrOF8E28w].mp4?raw=true"
        },
        {
            "id": "R2YzYOn4aWE",
            "name": "Mozart\uff1a Le nozze di Figaro, K. 492, Act I - No. 1, Duet. Cinque, dieci, venti [R2YzYOn4aWE].mp4",
            "path": "/home/alanmatzumiya/Videos/container/m4/videos/Mozart\uff1a Le nozze di Figaro, K. 492, Act I - No. 1, Duet. Cinque, dieci, venti [R2YzYOn4aWE].mp4",
            "size": 7.8487029999999995,
            "url": "https://github.com/circuitalmynds/music_m4/blob/main/videos/Mozart\uff1a Le nozze di Figaro, K. 492, Act I - No. 1, Duet. Cinque, dieci, venti [R2YzYOn4aWE].mp4?raw=true"
        },
        {
            "id": "81B74zIbTlU",
            "name": "Ravel - La vall\u00e9e des cloches {A Major} [81B74zIbTlU].mp4",
            "path": "/home/alanmatzumiya/Videos/container/m4/videos/Ravel - La vall\u00e9e des cloches {A Major} [81B74zIbTlU].mp4",
            "size": 15.963317,
            "url": "https://github.com/circuitalmynds/music_m4/blob/main/videos/Ravel - La vall\u00e9e des cloches {A Major} [81B74zIbTlU].mp4?raw=true"
        },
        {
            "id": "eaqG5yP8VoQ",
            "name": "Bidin' My Time [eaqG5yP8VoQ].mp4",
            "path": "/home/alanmatzumiya/Videos/container/m4/videos/Bidin' My Time [eaqG5yP8VoQ].mp4",
            "size": 9.391053,
            "url": "https://github.com/circuitalmynds/music_m4/blob/main/videos/Bidin' My Time [eaqG5yP8VoQ].mp4?raw=true"
        },
        {
            "id": "F8pglgiHa5w",
            "name": "Oh, Lady, Be Good! (Alternative Take 3) [F8pglgiHa5w].mp4",
            "path": "/home/alanmatzumiya/Videos/container/m4/videos/Oh, Lady, Be Good! (Alternative Take 3) [F8pglgiHa5w].mp4",
            "size": 14.634383,
            "url": "https://github.com/circuitalmynds/music_m4/blob/main/videos/Oh, Lady, Be Good! (Alternative Take 3) [F8pglgiHa5w].mp4?raw=true"
        },
        {
            "id": "eS_7_PCLFmY",
            "name": "Piramo e Tisbe\uff1a Aria\uff1a Infelice! In tanto orrore (Tisbe) [eS_7_PCLFmY].mp4",
            "path": "/home/alanmatzumiya/Videos/container/m4/videos/Piramo e Tisbe\uff1a Aria\uff1a Infelice! In tanto orrore (Tisbe) [eS_7_PCLFmY].mp4",
            "size": 7.976545,
            "url": "https://github.com/circuitalmynds/music_m4/blob/main/videos/Piramo e Tisbe\uff1a Aria\uff1a Infelice! In tanto orrore (Tisbe) [eS_7_PCLFmY].mp4?raw=true"
        },
        {
            "id": "97DJTxSdAss",
            "name": "Aquarellen, Walzer, Op. 258 [97DJTxSdAss].mp4",
            "path": "/home/alanmatzumiya/Videos/container/m4/videos/Aquarellen, Walzer, Op. 258 [97DJTxSdAss].mp4",
            "size": 32.37265,
            "url": "https://github.com/circuitalmynds/music_m4/blob/main/videos/Aquarellen, Walzer, Op. 258 [97DJTxSdAss].mp4?raw=true"
        },
        {
            "id": "dLMJhS3Z1Yo",
            "name": "Anton\u00edn Dvo\u0159\u00e1k - ALL HUMORESQUES FOR PIANO (7 THOUSAND SUBSCRIBERS TRIBUTE) [dLMJhS3Z1Yo].mp4",
            "path": "/home/alanmatzumiya/Videos/container/m4/videos/Anton\u00edn Dvo\u0159\u00e1k - ALL HUMORESQUES FOR PIANO (7 THOUSAND SUBSCRIBERS TRIBUTE) [dLMJhS3Z1Yo].mp4",
            "size": 44.258005999999995,
            "url": "https://github.com/circuitalmynds/music_m4/blob/main/videos/Anton\u00edn Dvo\u0159\u00e1k - ALL HUMORESQUES FOR PIANO (7 THOUSAND SUBSCRIBERS TRIBUTE) [dLMJhS3Z1Yo].mp4?raw=true"
        },
        {
            "id": "x46eGbMky-4",
            "name": "Keep It Together [x46eGbMky-4].mp4",
            "path": "/home/alanmatzumiya/Videos/container/m4/videos/Keep It Together [x46eGbMky-4].mp4",
            "size": 14.274476,
            "url": "https://github.com/circuitalmynds/music_m4/blob/main/videos/Keep It Together [x46eGbMky-4].mp4?raw=true"
        },
        {
            "id": "PBLwaj_8Akg",
            "name": "Qu\u00e9 Bueno Baila Usted [PBLwaj_8Akg].mp4",
            "path": "/home/alanmatzumiya/Videos/container/m4/videos/Qu\u00e9 Bueno Baila Usted [PBLwaj_8Akg].mp4",
            "size": 9.354877,
            "url": "https://github.com/circuitalmynds/music_m4/blob/main/videos/Qu\u00e9 Bueno Baila Usted [PBLwaj_8Akg].mp4?raw=true"
        },
        {
            "id": "_1CQdCZSzpg",
            "name": "Vremena goda, Op. 67\uff1a Summer\uff1a Coda [_1CQdCZSzpg].mp4",
            "path": "/home/alanmatzumiya/Videos/container/m4/videos/Vremena goda, Op. 67\uff1a Summer\uff1a Coda [_1CQdCZSzpg].mp4",
            "size": 6.801543,
            "url": "https://github.com/circuitalmynds/music_m4/blob/main/videos/Vremena goda, Op. 67\uff1a Summer\uff1a Coda [_1CQdCZSzpg].mp4?raw=true"
        },
        {
            "id": "Ly5spSa40VE",
            "name": "WERNER MULLER - GITANO (1967) LP [Ly5spSa40VE].mp4",
            "path": "/home/alanmatzumiya/Videos/container/m4/videos/WERNER MULLER - GITANO (1967) LP [Ly5spSa40VE].mp4",
            "size": 48.967406,
            "url": "https://github.com/circuitalmynds/music_m4/blob/main/videos/WERNER MULLER - GITANO (1967) LP [Ly5spSa40VE].mp4?raw=true"
        },
        {
            "id": "zJxTFUwRC9o",
            "name": "J.D.Heinichen\uff1a Concerto in D major for Flute, Oboe, Theorbo, Violin, Cello, Strings & B.c S.226 [zJxTFUwRC9o].mp4",
            "path": "/home/alanmatzumiya/Videos/container/m4/videos/J.D.Heinichen\uff1a Concerto in D major for Flute, Oboe, Theorbo, Violin, Cello, Strings & B.c S.226 [zJxTFUwRC9o].mp4",
            "size": 45.282139,
            "url": "https://github.com/circuitalmynds/music_m4/blob/main/videos/J.D.Heinichen\uff1a Concerto in D major for Flute, Oboe, Theorbo, Violin, Cello, Strings & B.c S.226 [zJxTFUwRC9o].mp4?raw=true"
        },
        {
            "id": "qZN1lwjBXPQ",
            "name": "Die Humoristiker-Walzer, Op. 92 [qZN1lwjBXPQ].mp4",
            "path": "/home/alanmatzumiya/Videos/container/m4/videos/Die Humoristiker-Walzer, Op. 92 [qZN1lwjBXPQ].mp4",
            "size": 16.404631,
            "url": "https://github.com/circuitalmynds/music_m4/blob/main/videos/Die Humoristiker-Walzer, Op. 92 [qZN1lwjBXPQ].mp4?raw=true"
        },
        {
            "id": "40_kUYaP4HE",
            "name": "Living Dangerously (feat. Bounty Killer) [40_kUYaP4HE].mp4",
            "path": "/home/alanmatzumiya/Videos/container/m4/videos/Living Dangerously (feat. Bounty Killer) [40_kUYaP4HE].mp4",
            "size": 7.3263869999999995,
            "url": "https://github.com/circuitalmynds/music_m4/blob/main/videos/Living Dangerously (feat. Bounty Killer) [40_kUYaP4HE].mp4?raw=true"
        },
        {
            "id": "XIkAFQ04VpQ",
            "name": "[I've Got] Beginner's Luck [XIkAFQ04VpQ].mp4",
            "path": "/home/alanmatzumiya/Videos/container/m4/videos/[I've Got] Beginner's Luck [XIkAFQ04VpQ].mp4",
            "size": 10.862478,
            "url": "https://github.com/circuitalmynds/music_m4/blob/main/videos/[I've Got] Beginner's Luck [XIkAFQ04VpQ].mp4?raw=true"
        },
        {
            "id": "kZGXsiI3r-E",
            "name": "Alessandro Rolla (1757-1841) - Divertimento \u00e0 Violino con Grande Orchestra [kZGXsiI3r-E].mp4",
            "path": "/home/alanmatzumiya/Videos/container/m4/videos/Alessandro Rolla (1757-1841) - Divertimento \u00e0 Violino con Grande Orchestra [kZGXsiI3r-E].mp4",
            "size": 64.491627,
            "url": "https://github.com/circuitalmynds/music_m4/blob/main/videos/Alessandro Rolla (1757-1841) - Divertimento \u00e0 Violino con Grande Orchestra [kZGXsiI3r-E].mp4?raw=true"
        },
        {
            "id": "klQY_X1clMs",
            "name": "Igor Stravinsky - Ebony Concerto [With score] [klQY_X1clMs].mp4",
            "path": "/home/alanmatzumiya/Videos/container/m4/videos/Igor Stravinsky - Ebony Concerto [With score] [klQY_X1clMs].mp4",
            "size": 18.561892,
            "url": "https://github.com/circuitalmynds/music_m4/blob/main/videos/Igor Stravinsky - Ebony Concerto [With score] [klQY_X1clMs].mp4?raw=true"
        },
        {
            "id": "UfOfO3-sfMY",
            "name": "Mozart\uff1a Le nozze di Figaro, K. 492, Act IV - No. 25, Il capro e la capretta [UfOfO3-sfMY].mp4",
            "path": "/home/alanmatzumiya/Videos/container/m4/videos/Mozart\uff1a Le nozze di Figaro, K. 492, Act IV - No. 25, Il capro e la capretta [UfOfO3-sfMY].mp4",
            "size": 9.156784,
            "url": "https://github.com/circuitalmynds/music_m4/blob/main/videos/Mozart\uff1a Le nozze di Figaro, K. 492, Act IV - No. 25, Il capro e la capretta [UfOfO3-sfMY].mp4?raw=true"
        },
        {
            "id": "SSc98EY08Jc",
            "name": "Las Chicanas [SSc98EY08Jc].mp4",
            "path": "/home/alanmatzumiya/Videos/container/m4/videos/Las Chicanas [SSc98EY08Jc].mp4",
            "size": 4.350388,
            "url": "https://github.com/circuitalmynds/music_m4/blob/main/videos/Las Chicanas [SSc98EY08Jc].mp4?raw=true"
        },
        {
            "id": "HBEMuP_PtiI",
            "name": "Laid Back - Brother [HBEMuP_PtiI].mp4",
            "path": "/home/alanmatzumiya/Videos/container/m4/videos/Laid Back - Brother [HBEMuP_PtiI].mp4",
            "size": 19.785943,
            "url": "https://github.com/circuitalmynds/music_m4/blob/main/videos/Laid Back - Brother [HBEMuP_PtiI].mp4?raw=true"
        }
    ],
    "total_size": 949.5950949999999
}